diskdict/__init__.py
diskdict/command.py
diskdict/diskdict.py
diskdict/strtoint.py
diskdict-0.2.5.dist-info/LICENSE
diskdict-0.2.5.dist-info/METADATA
diskdict-0.2.5.dist-info/WHEEL
diskdict-0.2.5.dist-info/entry_points.txt
diskdict-0.2.5.dist-info/top_level.txt
diskdict-0.2.5.dist-info/RECORD
