Metadata-Version: 2.1
Name: diskdict
Version: 0.2.5
Summary: A dict like datastructure on disk
Home-page: https://github.com/deep-compute/diskdict
Author: Deep Compute, LLC
Author-email: contact@deepcompute.com
License: MIT License
Download-URL: https://github.com/deep-compute/diskdict/tarball/0.2.5
Keywords: diskdict
Platform: UNKNOWN
Classifier: Programming Language :: Python :: 3.5
Classifier: Programming Language :: Python :: 2.7
Classifier: Environment :: Console
Classifier: Intended Audience :: Developers
Classifier: License :: OSI Approved :: MIT License
Requires-Dist: deeputil (==0.2.7)
Requires-Dist: basescript (==0.2.9)
Requires-Dist: plyvel (==1.0.4)
Requires-Dist: cmph-cffi (==0.3.0)
Requires-Dist: diskarray (==0.1.9)
Requires-Dist: numpy (==1.14.3)
